liteswarm/__init__.py
liteswarm/py.typed
liteswarm/chat/__init__.py
liteswarm/chat/chat.py
liteswarm/chat/context.py
liteswarm/chat/summarizer.py
liteswarm/chat/vector_index.py
liteswarm/core/__init__.py
liteswarm/core/swarm.py
liteswarm/core/swarm_stream.py
liteswarm/repl/__init__.py
liteswarm/repl/event_handler.py
liteswarm/repl/repl.py
liteswarm/types/__init__.py
liteswarm/types/agent.py
liteswarm/types/base.py
liteswarm/types/chat.py
liteswarm/types/collections.py
liteswarm/types/context.py
liteswarm/types/events.py
liteswarm/types/exceptions.py
liteswarm/types/llm.py
liteswarm/types/swarm.py
liteswarm/types/tools.py
liteswarm/types/typing.py
liteswarm/types/utils.py
liteswarm/utils/__init__.py
liteswarm/utils/function.py
liteswarm/utils/logging.py
liteswarm/utils/messages.py
liteswarm/utils/misc.py
liteswarm/utils/pydantic.py
liteswarm/utils/retry.py
liteswarm/utils/usage.py
liteswarm-0.6.0.dist-info/LICENSE
liteswarm-0.6.0.dist-info/METADATA
liteswarm-0.6.0.dist-info/WHEEL
liteswarm-0.6.0.dist-info/top_level.txt
liteswarm-0.6.0.dist-info/RECORD
