Metadata-Version: 2.2
Name: liteswarm
Version: 0.6.0
Summary: A lightweight framework for building AI agent systems
Author-email: Evgenii Mozharovskii <eugene@glyphy.ai>
License: MIT License
Project-URL: homepage, https://github.com/GlyphyAI/liteswarm
Project-URL: repository, https://github.com/GlyphyAI/liteswarm
Project-URL: documentation, https://github.com/GlyphyAI/liteswarm#readme
Project-URL: bug-tracker, https://github.com/GlyphyAI/liteswarm/issues
Project-URL: changelog, https://github.com/GlyphyAI/liteswarm/blob/main/CHANGELOG.md
Keywords: ai,agents,llm,swarm,multi-agent,agent-systems,agent-orchestration
Classifier: Development Status :: 3 - Alpha
Classifier: Intended Audience :: Developers
Classifier: Intended Audience :: Science/Research
Classifier: License :: OSI Approved :: MIT License
Classifier: Programming Language :: Python :: 3
Classifier: Programming Language :: Python :: 3.11
Classifier: Topic :: Software Development :: Libraries :: Python Modules
Classifier: Topic :: Scientific/Engineering :: Artificial Intelligence
Requires-Python: >=3.11
License-File: LICENSE
Requires-Dist: griffe>=1.5.1
Requires-Dist: json-repair>=0.30.2
Requires-Dist: litellm>=1.57.1
Requires-Dist: numpy>=2.2.0
Requires-Dist: orjson>=3.10.11
Requires-Dist: pydantic>=2.10.5
Requires-Dist: prompt_toolkit>=3.0.48
Provides-Extra: dev
Requires-Dist: mypy>=1.14.1; extra == "dev"
Requires-Dist: ruff>=0.7.3; extra == "dev"
Requires-Dist: pytest>=8.3.4; extra == "dev"
Requires-Dist: pytest-asyncio>=0.25.1; extra == "dev"
Requires-Dist: typing-extensions>=4.12.2; extra == "dev"
Requires-Dist: commitizen>=4.1.0; extra == "dev"
Provides-Extra: docs
Requires-Dist: mkdocs>=1.5.3; extra == "docs"
Requires-Dist: mkdocs-material>=9.5.13; extra == "docs"
Requires-Dist: mkdocstrings>=0.24.1; extra == "docs"
Requires-Dist: mkdocstrings-python>=1.9.0; extra == "docs"
Requires-Dist: mdx-truly-sane-lists>=1.3; extra == "docs"
Provides-Extra: examples
Requires-Dist: fastapi>=0.115.6; extra == "examples"
Requires-Dist: uvicorn>=0.34.0; extra == "examples"
